inspire_utils/__init__.py
inspire_utils/config.py
inspire_utils/date.py
inspire_utils/dedupers.py
inspire_utils/helpers.py
inspire_utils/isbn.py
inspire_utils/logging.py
inspire_utils/name.py
inspire_utils/query.py
inspire_utils/record.py
inspire_utils/urls.py
inspire_utils-3.0.67.dist-info/licenses/LICENSE
inspire_utils-3.0.67.dist-info/METADATA
inspire_utils-3.0.67.dist-info/WHEEL
inspire_utils-3.0.67.dist-info/top_level.txt
inspire_utils-3.0.67.dist-info/RECORD
