Metadata-Version: 2.4
Name: inspire-utils
Version: 3.0.67
Summary: INSPIRE-specific utils.
Home-page: https://github.com/inspirehep/inspire-utils
Author: CERN
Author-email: admin@inspirehep.net
License: GPLv3
Platform: any
Classifier: Development Status :: 4 - Beta
Classifier: Environment :: Web Environment
Classifier: Intended Audience :: Developers
Classifier: License :: OSI Approved :: GNU General Public License v3 (GPLv3)
Classifier: Operating System :: OS Independent
Classifier: Programming Language :: Python
Classifier: Programming Language :: Python :: 2
Classifier: Programming Language :: Python :: 2.7
Classifier: Programming Language :: Python :: 3
Classifier: Programming Language :: Python :: 3.6
Classifier: Programming Language :: Python :: 3.7
Classifier: Programming Language :: Python :: 3.8
Classifier: Programming Language :: Python :: 3.9
Classifier: Programming Language :: Python :: 3.10
Classifier: Programming Language :: Python :: 3.11
Classifier: Programming Language :: Python :: 3.12
Classifier: Topic :: Internet :: WWW/HTTP :: Dynamic Content
Classifier: Topic :: Software Development :: Libraries :: Python Modules
License-File: LICENSE
Requires-Dist: Unidecode>=1.2.0,~=1.0
Requires-Dist: babel>=2.9.1,~=2.9
Requires-Dist: lxml~=5.0
Requires-Dist: nameparser>=1.1.3,~=1.1
Requires-Dist: python-dateutil>=2.9.0,~=2.9
Requires-Dist: six>=1.10.0,~=1.0
Requires-Dist: isbnlib>=3.10.14,~=3.10
Provides-Extra: docs
Provides-Extra: tests
Requires-Dist: flake8-future-import>=0.4.3,~=0.0; extra == "tests"
Requires-Dist: mock>=2.0.0,~=2.0; extra == "tests"
Provides-Extra: dev
Requires-Dist: pre-commit==3.5.0; extra == "dev"
Requires-Dist: unicode-string-literal>=1.1,~=1.0; python_version == "2.7" and extra == "tests"
Requires-Dist: pytest>=4.6.0,~=4.0; python_version == "2.7" and extra == "tests"
Requires-Dist: pytest>=8.2.2,~=8.0; python_version >= "3" and extra == "tests"
Provides-Extra: all
Requires-Dist: flake8-future-import>=0.4.3,~=0.0; extra == "all"
Requires-Dist: mock>=2.0.0,~=2.0; extra == "all"
Requires-Dist: pre-commit==3.5.0; extra == "all"
Requires-Dist: unicode-string-literal>=1.1,~=1.0; extra == "all"
Requires-Dist: pytest>=4.6.0,~=4.0; extra == "all"
Requires-Dist: pytest>=8.2.2,~=8.0; extra == "all"
Requires-Dist: flake8-future-import>=0.4.3,~=0.0; extra == "all"
Requires-Dist: mock>=2.0.0,~=2.0; extra == "all"
Requires-Dist: pre-commit==3.5.0; extra == "all"
Requires-Dist: unicode-string-literal>=1.1,~=1.0; extra == "all"
Requires-Dist: pytest>=4.6.0,~=4.0; extra == "all"
Requires-Dist: pytest>=8.2.2,~=8.0; extra == "all"
Dynamic: author
Dynamic: author-email
Dynamic: classifier
Dynamic: description
Dynamic: description-content-type
Dynamic: home-page
Dynamic: license
Dynamic: license-file
Dynamic: platform
Dynamic: provides-extra
Dynamic: requires-dist
Dynamic: summary
